bankroll/marketdata/__init__.py
bankroll/marketdata/broker.py
bankroll/marketdata/provider.py
bankroll/marketdata/py.typed
bankroll_marketdata-0.4.0.dist-info/LICENSE
bankroll_marketdata-0.4.0.dist-info/METADATA
bankroll_marketdata-0.4.0.dist-info/WHEEL
bankroll_marketdata-0.4.0.dist-info/top_level.txt
bankroll_marketdata-0.4.0.dist-info/RECORD
